{"nodes": [{"id": "colors", "label": "colors.ts", "file_type": "code", "source_file": "packages\\types\\src\\colors.ts", "source_location": "L1"}, {"id": "colors_isfreecolor", "label": "isFreeColor()", "file_type": "code", "source_file": "packages\\types\\src\\colors.ts", "source_location": "L74"}], "edges": [{"source": "colors", "target": "colors_isfreecolor", "relation": "contains", "confidence": "EXTRACTED", "source_file": "packages\\types\\src\\colors.ts", "source_location": "L74", "weight": 1.0}]}