{"nodes": [{"id": "page", "label": "page.tsx", "file_type": "code", "source_file": "apps\\web_v2\\app\\design\\page.tsx", "source_location": "L1"}, {"id": "page_designpage", "label": "DesignPage()", "file_type": "code", "source_file": "apps\\web_v2\\app\\design\\page.tsx", "source_location": "L10"}], "edges": [{"source": "page", "target": "next", "relation": "imports_from", "confidence": "EXTRACTED", "source_file": "apps\\web_v2\\app\\design\\page.tsx", "source_location": "L1", "weight": 1.0}, {"source": "page", "target": "design_content", "relation": "imports_from", "confidence": "EXTRACTED", "source_file": "apps\\web_v2\\app\\design\\page.tsx", "source_location": "L2", "weight": 1.0}, {"source": "page", "target": "page_designpage", "relation": "contains", "confidence": "EXTRACTED", "source_file": "apps\\web_v2\\app\\design\\page.tsx", "source_location": "L10", "weight": 1.0}]}